TLA/__init__.py
TLA/Analysis/__init__.py
TLA/Analysis/analyse.py
TLA/Analysis/get_sentiment.py
TLA/Analysis/lang_mapping.py
TLA/Analysis/table_1.py
TLA/Analysis/table_2.py
TLA/Analysis/train_rf.py
TLA/Data/Pre_Process_Tweets.py
TLA/Data/__init__.py
TLA/Data/get_data.py
TLA/Data/get_tweets.py
TLA/Datasets/get_data_en.csv
TLA/Datasets/get_data_es.csv
TLA/Datasets/get_data_fa.csv
TLA/Datasets/get_data_fr.csv
TLA/Datasets/get_data_hi.csv
TLA/Datasets/get_data_id.csv
TLA/Datasets/get_data_ja.csv
TLA/Datasets/get_data_nl.csv
TLA/Datasets/get_data_pt.csv
TLA/Datasets/get_data_ro.csv
TLA/Datasets/get_data_ru.csv
TLA/Datasets/get_data_sv.csv
TLA/Datasets/get_data_th.csv
TLA/Datasets/get_data_tr.csv
TLA/Datasets/get_data_ur.csv
TLA/Datasets/get_data_zh-cn.csv
TLA/Datasets/get_lang_data.py
TLA/Lang_Classify/model.py
TLA/Lang_Classify/predict.py
TLA/Lang_Classify/train.py
TLA/Lang_Classify/training_utils.py
TLAF-1.1.dist-info/License.txt
TLAF-1.1.dist-info/METADATA
TLAF-1.1.dist-info/WHEEL
TLAF-1.1.dist-info/top_level.txt
TLAF-1.1.dist-info/RECORD
