Metadata-Version: 2.1
Name: TLAF
Version: 1.1
Summary: TLA is built using PyTorch, Transformers and several other State-of-the-Art machine learning techniques and it aims to expedite and structure the cumbersome process of collecting, labeling, and analyzing data from Twitter for a corpus of languages while providing detailed labeled datasets for all the languages.
Home-page: https://github.com/tusharsarkar3/TLA
Author: Tushar Sarkar , Nishant Rajadhyaksha
Author-email: tushar.sarkar@somaiya.edu, n.rajadhyaksha@somaiya.edu
License: MIT
Platform: UNKNOWN
Classifier: Programming Language :: Python :: 3
Classifier: License :: OSI Approved :: MIT License
Classifier: Operating System :: OS Independent
Requires-Dist: beautifulsoup4 (==4.9.3)
Requires-Dist: certifi (==2021.5.30)
Requires-Dist: charset-normalizer (==2.0.3)
Requires-Dist: click (==8.0.1)
Requires-Dist: colorama (==0.4.4)
Requires-Dist: cycler (==0.10.0)
Requires-Dist: filelock (==3.0.12)
Requires-Dist: huggingface-hub (==0.0.12)
Requires-Dist: idna (==3.2)
Requires-Dist: joblib (==1.0.1)
Requires-Dist: kiwisolver (==1.3.1)
Requires-Dist: lxml (==4.6.3)
Requires-Dist: matplotlib (==3.4.2)
Requires-Dist: nltk (==3.6.2)
Requires-Dist: numpy (==1.21.1)
Requires-Dist: packaging (==21.0)
Requires-Dist: pandas (==1.3.0)
Requires-Dist: Pillow (==8.3.1)
Requires-Dist: pyparsing (==2.4.7)
Requires-Dist: PySocks (==1.7.1)
Requires-Dist: python-dateutil (==2.8.2)
Requires-Dist: pytz (==2021.1)
Requires-Dist: PyYAML (==5.4.1)
Requires-Dist: regex (==2021.7.6)
Requires-Dist: requests (==2.26.0)
Requires-Dist: sacremoses (==0.0.45)
Requires-Dist: scikit-learn (==0.24.2)
Requires-Dist: scipy (==1.7.0)
Requires-Dist: six (==1.16.0)
Requires-Dist: sklearn (==0.0)
Requires-Dist: snscrape (==0.3.4)
Requires-Dist: soupsieve (==2.2.1)
Requires-Dist: threadpoolctl (==2.2.0)
Requires-Dist: tokenizers (==0.10.3)
Requires-Dist: torch (==1.9.0)
Requires-Dist: tqdm (==4.61.2)
Requires-Dist: transformers (==4.8.2)
Requires-Dist: typing-extensions (==3.10.0.0)
Requires-Dist: urllib3 (==1.26.6)
